pelican/plugins/touch/__init__.py
pelican/plugins/touch/touch.py
pelican_touch-1.0.0.dist-info/LICENSE
pelican_touch-1.0.0.dist-info/METADATA
pelican_touch-1.0.0.dist-info/WHEEL
pelican_touch-1.0.0.dist-info/RECORD
